rfc5234/__init__.py
rfc5234/ast.py
rfc5234/context.py
rfc5234/defs.py
rfc5234/exc.py
rfc5234/expr.py
rfc5234/py.typed
rfc5234/rfc5234.py
rfc5234/simple_expr.py
rfc5234/tokenize.py
rfc5234/util.py
rfc5234/abnf/__init__.py
rfc5234/abnf/abnf.abnf
rfc5234/abnf/abnf_original.abnf
rfc5234/abnf/core.abnf
rfc5234/abnf/json.abnf
rfc5234/abnf/simple_expr.abnf
rfc5234/abnf/toml.abnf
rfc5234-0.1.6.dist-info/METADATA
rfc5234-0.1.6.dist-info/WHEEL
rfc5234-0.1.6.dist-info/licenses/LICENSE
rfc5234-0.1.6.dist-info/RECORD
